iocpy/__init__.py
iocpy/ioc_container.py
iocpy/ioc_context.py
iocpy/ioc_registry.py
iocpy/py.typed
iocpy/behaviors/__init__.py
iocpy/behaviors/scoped.py
iocpy/behaviors/singleton.py
iocpy/behaviors/transient.py
iocpy/interfaces/__init__.py
iocpy/interfaces/behavior_registry.py
iocpy/interfaces/instance_behavior.py
iocpy/interfaces/instance_provider.py
iocpy/interfaces/ioc_context.py
iocpy3-0.1.1.dist-info/METADATA
iocpy3-0.1.1.dist-info/WHEEL
iocpy3-0.1.1.dist-info/licenses/LICENSE
iocpy3-0.1.1.dist-info/RECORD
