Metadata-Version: 2.4
Name: iocpy3
Version: 0.1.1
Summary: Simple ioc framework for python
Project-URL: Repository, https://github.com/MkKiefer/iocpy.git
Project-URL: Issues, https://github.com/MkKiefer/iocpy/issues
Author: MkKiefer
License-Expression: MIT
License-File: LICENSE
Requires-Python: >=3.11
